{"abGroup": 0, "abUseExperiments": [{"experimentName": "aud_desktop_aud3558_expert_opinion_gpt", "groupName": "C"}, {"experimentName": "newbuilding_flatsale_trap_desktop", "groupName": "C"}, {"experimentName": "newbuilding_new_entry_point_webim_desktop", "groupName": "B"}, {"experimentName": "newbuilding_rent_trap_desktop", "groupName": null}, {"experimentName": "newbuilding_suburban_trap_desktop", "groupName": "C"}, {"experimentName": "newbuilding_trust_safety_desktop", "groupName": "enabled"}], "aside": {"height": 0, "isNavigationActive": false, "activeAnchor": "#photos", "isCompactModeEnabled": false}, "hideOffer": {}, "bookedOfferId": 0, "captchaSiteKey": "6LfvfCETAAAAABxHQ2wxiTT_mILt0c87axZn7zOU", "captchaSpamSiteKey": "6LdpqSQUAAAAAJXo9mQJY2QYw2rSi2D0-ZXctcw_", "commentsData": {"commentText": "", "editing": false, "isOpen": false, "messageError": "", "statusFetch": "none", "openAfterAuth": false}, "favoriteMotivation": {"isActive": true, "isShows": false}, "feedback": {"isComplaintPopupOpened": false, "isFeedbackSent": false, "isFeedbackSentPopupOpened": false, "isFormPopupOpened": false, "isPopupOpened": false, "status": "Initial"}, "gallery": {}, "legend": {"isOpen": false}, "mapSimilar": null, "mapTabs": {"activeTab": "similarOffers"}, "mortgage": {"rates": {"flat": {"used": 22.99, "new": 5.99}, "appartments": {"used": 23.49, "new": 22.99}, "suburban": {"new": 6, "used": 25.9}}, "bankIds": ["bank-alfa", "bank-domrf", "bank-mkb", "bank-sovcom", "bank-t", "bank-uralsib", "bank-vtb-new"]}, "mortgageGallery": {}, "newbuildingBookedFromDeveloper": {"isConfirmOpen": false, "status": "initial"}, "newbuildingChat": {"userData": null, "isOpen": false}, "newbuildingConsultant": {"accountName": "cianru008", "consultantPhoneEnabledRegions": [1, 4593, -1], "location": "reserve"}, "offerChat": {"isChatsEnabled": true, "isChatOpened": false, "openAfterAuth": false, "isOnline": false, "hintQuestions": [{"analyticsKey": "contactMe", "buttonText": "Свяжитесь со мной", "messageText": "Здравствуйте. Пожалуйста, свяжитесь со мной ", "payload": null}, {"analyticsKey": "whenSee", "buttonText": "Хочу посмотреть", "messageText": "Здравствуйте. Подскажите, пожалуйста, когда можно посмотреть квартиру?", "payload": null}, {"analyticsKey": "stillSelling", "buttonText": "Ещё продаёте?", "messageText": "Здравствуйте. Уточните, пожалуйста, вы ещё продаёте эту квартиру?", "payload": null}]}, "offerData": {"offer": {"category": "flatSale", "status": "published", "dealType": "sale", "offerType": "flat", "geo": {"address": [{"fullName": "Москва", "id": 1, "locationTypeId": 1, "name": "Москва", "shortName": "Москва", "type": "location", "url": "https://www.cian.ru/kupit-2-komnatnuyu-kvartiru/"}, {"fullName": "ЮЗАО", "id": 10, "locationTypeId": -1, "name": "ЮЗАО", "shortName": "ЮЗАО", "type": "okrug", "url": "https://www.cian.ru/kupit-2-komnatnuyu-kvartiru-moskva-yuzao-0410/"}, {"fullName": "район Ломоносовский", "id": 105, "locationTypeId": -1, "name": "Ломоносовский", "shortName": "р-н Ломоносовский", "type": "raion", "url": "https://www.cian.ru/kupit-2-komnatnuyu-kvartiru-moskva-lomonosovskiy-04105/"}, {"fullName": "улица Архитектора Власова", "id": 794, "locationTypeId": -1, "name": "Архитектора Власова", "shortName": "ул. Архитектора Власова", "type": "street", "url": "https://www.cian.ru/kupit-2-komnatnuyu-kvartiru-moskva-ulica-arhitektora-vlasova-02794/"}, {"fullName": "6", "id": 1692975, "locationTypeId": -1, "name": "6", "shortName": "6", "type": "house", "url": "https://www.cian.ru/cat.php?deal_type=sale&engine_version=2&house%5B0%5D=1692975&offer_type=flat&room2=1"}], "coordinates": {"lat": 55.679605, "lng": 37.550333}, "highways": [], "jk": {"id": 45932, "name": "Вавилово", "house": {"id": 102962, "name": "Дом 6"}, "gaGeo": {"moId": 0, "oblId": 1, "cityId": 1}, "fullUrl": "https://www.cian.ru/zhiloy-kompleks-vavilovo-moskva-45932/", "fullUrlTemplate": "{request_scheme}://zhk-vavilovo-i.{host}/", "webSiteUrl": "https://vavilovo.com/"}, "railways": [{"id": 709, "directionIds": [17], "distance": "5.0", "time": 71, "name": "Нижние Котлы", "travelType": "byFoot"}, {"id": 709, "directionIds": [17], "distance": "6.0", "time": 12, "name": "Нижние Котлы", "travelType": "byCar"}, {"id": 723, "directionIds": [17], "distance": "6.0", "time": 11, "name": "Коломенское", "travelType": "byCar"}, {"id": 723, "directionIds": [17], "distance": "6.0", "time": 76, "name": "Коломенское", "travelType": "byFoot"}, {"id": 716, "directionIds": [14], "distance": "6.0", "time": 78, "name": "Матвеевская", "travelType": "byFoot"}, {"id": 716, "directionIds": [14], "distance": "8.0", "time": 13, "name": "Матвеевская", "travelType": "byCar"}], "undergrounds": [{"id": 104, "name": "Профсоюзная", "lineColor": "FF7F00", "travelType": "walk", "travelTime": 12, "url": "https://www.cian.ru/kupit-2-komnatnuyu-kvartiru-moskva-metro-profsoyuznaya/", "underConstruction": false}, {"id": 79, "name": "Новые Черёмушки", "lineColor": "FF7F00", "travelType": "walk", "travelTime": 16, "url": "https://www.cian.ru/kupit-2-komnatnuyu-kvartiru-moskva-metro-novye-cheremushki/", "underConstruction": false}, {"id": 541, "name": "Вавиловская", "lineColor": "03795F", "travelType": "walk", "travelTime": 17, "url": "https://www.cian.ru/kupit-2-komnatnuyu-kvartiru-moskva-metro-vavilovskaya/", "releaseYear": 2026, "underConstruction": true}]}, "id": 298271416, "objectGuid": "ecb3102e-8816-4a8a-9f02-e5307f8ea75b", "cianId": 298271416, "userId": 5556693, "publishedUserId": 90141535, "cianUserId": 90141535, "description": "Id 1588. Делимся с коллегами 50/50. Настоящий бизнес класс в готовом доме от 300.000т. м²!\nО квартире: \nПродается просторная 2х-комнатная квартира, с возможностью перепланировки в две изолированные комнаты. Квартира в качественной и продуманной отделке white-box, что позволит вам реализовать свои творческие задумки, в процессе ремонта. Комнаты в квартире площадями 41.4 кв.м. и 22.7 кв.м. \n \nО локации:\nЭто место жительства научной элиты страны, академиков, композиторов, писателей. Дом расположен в современном районе Москвы с устоявшейся инфраструктурой, трех-уровневый подземный паркинг, эксплуатируемая кровля на которой вы всегда можете провести время наблюдая панораму города на 360 градусов.  В непосредственной близости расположен знаменитый Черемушкинский рынок, который в 1962 году открывал сам генеральный секретарь Л.И. Брежнев. В ЖК находятся детский сад, школа, медицинские центры.\n\nО транспортной доступности:\nШикарное местоположение: комфортно добираться до центра города как общественным транспортом, так и на личном авто. До метро Профсоюзная пешком 10 минут.\n\nО документах:\nПолная стоимость в договоре\nКвартира без обременений\nСвободная продажа.\n\n\nБлижайшие станции метро (по прямой):\nм. Профсоюзная - 700 метров\nм. Новые Черёмушки - 900 метров\nм. Академическая - 1600 метров", "photos": [{"id": 2095952382, "isDefault": false, "fullUrl": "https://images.cdn-cian.ru/images/2095952382-1.jpg", "thumbnailUrl": "https://images.cdn-cian.ru/images/2095952382-2.jpg", "thumbnail2Url": "https://images.cdn-cian.ru/images/2095952382-4.jpg", "miniUrl": "https://images.cdn-cian.ru/images/2095952382-3.jpg", "isLayout": false, "isCianLayout": false}, {"id": 2095952383, "isDefault": false, "fullUrl": "https://images.cdn-cian.ru/images/2095952383-1.jpg", "thumbnailUrl": "https://images.cdn-cian.ru/images/2095952383-2.jpg", "thumbnail2Url": "https://images.cdn-cian.ru/images/2095952383-4.jpg", "miniUrl": "https://images.cdn-cian.ru/images/2095952383-3.jpg", "isLayout": true, "isCianLayout": false}, {"id": 2095952387, "isDefault": false, "fullUrl": "https://images.cdn-cian.ru/images/2095952387-1.jpg", "thumbnailUrl": "https://images.cdn-cian.ru/images/2095952387-2.jpg", "thumbnail2Url": "https://images.cdn-cian.ru/images/2095952387-4.jpg", "miniUrl": "https://images.cdn-cian.ru/images/2095952387-3.jpg", "isLayout": false, "isCianLayout": false}, {"id": 2095952397, "isDefault": false, "fullUrl": "https://images.cdn-cian.ru/images/2095952397-1.jpg", "thumbnailUrl": "https://images.cdn-cian.ru/images/2095952397-2.jpg", "thumbnail2Url": "https://images.cdn-cian.ru/images/2095952397-4.jpg", "miniUrl": "https://images.cdn-cian.ru/images/2095952397-3.jpg", "isLayout": false, "isCianLayout": false}, {"id": 2095952407, "isDefault": false, "fullUrl": "https://images.cdn-cian.ru/images/2095952407-1.jpg", "thumbnailUrl": "https://images.cdn-cian.ru/images/2095952407-2.jpg", "thumbnail2Url": "https://images.cdn-cian.ru/images/2095952407-4.jpg", "miniUrl": "https://images.cdn-cian.ru/images/2095952407-3.jpg", "isLayout": false, "isCianLayout": false}], "phones": [{"countryCode": "+7", "number": "9810865337"}, {"countryCode": "+7", "number": "9660590489"}], "publishTerms": {"terms": [{"services": ["paid"], "days": 30, "type": "periodical", "tariffIdentificator": {"tariffId": 9651341, "tariffGridType": "servicePackageGroup"}}], "autoprolong": true}, "flatType": "rooms", "totalArea": "122.4", "livingArea": "64.1", "kitchenArea": "19.3", "allRoomsArea": "41.4-22.7", "windowsViewType": "yard", "combinedWcsCount": 2, "repairType": "no", "flags": {"isArchived": false, "isCommercialOwnershipVerified": false}, "specialty": {"types": [], "additionalTypes": []}, "isNeedHideExactAddress": false, "areaParts": [], "roomsCount": 2, "floorNumber": 2, "bargainTerms": {"price": 42000000, "priceType": "all", "currency": "rur", "mortgageAllowed": true, "saleType": "free", "includedOptions": [], "agentBonus": {"paymentType": "fixed", "value": 0, "currency": "rur"}, "prices": {"rur": 42000000, "usd": 459345, "eur": 438392}, "tags": []}, "building": {"materialType": "monolith", "floorsCount": 18, "buildYear": 2005, "parking": {"type": "underground"}, "ceilingHeight": "3.0", "series": "Индивидуальный проект", "totalArea": "122.4", "liftTypes": [], "cranageTypes": [], "passengerLiftsCount": 1, "cargoLiftsCount": 1, "houseMaterialType": "monolith"}, "editDate": "2025-02-17T19:10:19.791813+00:00", "humanizedEditDate": "17 фев, 19:10", "isInHiddenBase": false, "isObjectHidden": false, "isClosedVisibility": false, "videos": [], "demolishedInMoscowProgramm": false, "priceTotal": 42000000, "priceTotalRur": 42000000, "exportLinks": {"pdfUrl": "/export/pdf/sale/flat/298271416/", "docxUrl": "/export/docx/sale/flat/298271416/"}, "passengerLiftsCount": 1, "cargoLiftsCount": 1, "added": "24 янв, 10:45", "valueAddedServices": {"isStandard": false, "isTop3": false, "isPremium": false}, "categoriesIds": [1, 100, 110, 111], "publicationDate": 1707316060, "creationDate": "2024-02-07T17:27:40.41", "recoveryLink": "/razmestit-obyavlenie/298271416/?isFromXML=1", "isFromBuilder": false, "isFromSeller": false, "isFromLeadFactory": false, "trackingData": {"moId": 0, "oblId": 1, "cityId": 1, "fbRegion": "Москва", "fbCity": "Москва"}, "editPhoto": "/realty/add2.aspx?id=298271416&isFromXML=1", "newEdit": "/razmestit-obyavlenie/?realty_id=298271416&isFromXML=1", "certificate": "https://www.cian.ru/newobjects/cian/certification/get?announcementId=298271416", "edit": "/realty/add1.aspx?id=298271416&isFromXML=1", "similarOffersLink": "", "similarOffersCount": 0, "buildersIds": [13106], "isImported": true, "userConfirmedFix": false, "newbuilding": {"id": 45932, "name": "Вавилово", "house": {"isReliable": false, "isFinished": true, "finishDate": {"quarter": 1, "year": 2005}, "id": 102962, "name": "Дом 6"}, "isFromDeveloper": false, "isFromBuilder": false, "isFromSeller": false, "isFromLeadFactory": false, "showJkReliableFlag": false, "isFichering": false, "isFicheringPlus": false, "isPremium": false, "newbuildingFeatures": {"imagesCount": 3, "firstImageUrl": "https://images.cdn-cian.ru/images/2/343/886/vavilovo-moskva-jk-688343248-6.jpg", "videosCount": 0, "deadlineInfo": "Сдан"}, "isReliable": false, "isTariffPremium": false}, "timezone": 3, "isEnabledCallTracking": true, "callTrackingProvider": "beeline", "isRentByParts": false, "isDuplicate": false, "userTrust": "involved", "userTrustLevel": "involved", "showWarningMessage": false, "moderationInfo": {"showContactWarningMessage": false}, "isUnique": false, "isUniqueCheckDate": "2025-02-18", "isCianPartner": false, "externalId": "1588", "isIllegalConstruction": false, "externalOfferUrl": "", "cianLayouts": null}, "seoLinks": [], "breadcrumbs": [{"url": "https://www.cian.ru/", "title": "Недвижимость в Москве"}, {"url": "https://www.cian.ru/kupit/", "title": "Продажа"}, {"url": "https://www.cian.ru/kupit-2-komnatnuyu-kvartiru/", "title": "Продажа 2-комнатных квартир в Москве"}, {"url": "https://www.cian.ru/kupit-2-komnatnuyu-kvartiru-moskva-yuzao-0410/", "title": "ЮЗАО"}, {"url": "https://www.cian.ru/kupit-2-komnatnuyu-kvartiru-moskva-lomonosovskiy-04105/", "title": "Ломоносовский"}, {"url": "https://www.cian.ru/kupit-2-komnatnuyu-kvartiru-moskva-metro-profsoyuznaya/", "title": "метро Профсоюзная"}, {"url": "https://www.cian.ru/kupit-2-komnatnuyu-kvartiru-moskva-ulica-arhitektora-vlasova-02794/", "title": "улица Архитектора Власова"}], "similarOffersMapQs": "engine_version=2&deal_type=sale&offer_type=flat&region=1&minprice=35700000&maxprice=48299999&room2=1&room3=1", "similarNewObjects": [{"id": 301259851, "photoUrl": "https://images.cdn-cian.ru/images/2361578848-4.jpg", "roomTitle": "2-комн. кв", "addressStr": "Москва, Севастопольский просп., 22А", "floor": 42, "floorn": 35, "kitchenArea": 0, "livingArea": 15, "priceRur": 29721600, "publishedUserId": 39404589, "totalArea": 43, "undergroundInfo": {"lineColor": "A2A5B5", "name": "Нагорная", "type": "mow"}}, {"id": 313877476, "photoUrl": "https://images.cdn-cian.ru/images/2405805657-4.jpg", "roomTitle": "2-комн. кв", "addressStr": "Москва, Левел Мичуринский жилой комплекс, к5", "floor": 37, "floorn": 35, "kitchenArea": 19.9, "livingArea": 14.1, "priceRur": 31227126, "publishedUserId": 98302806, "totalArea": 51.6, "undergroundInfo": {"lineColor": "FFDF00", "name": "Мичуринский проспект", "type": "mow"}}, {"id": 313796589, "photoUrl": "https://images.cdn-cian.ru/images/2403792986-4.jpg", "roomTitle": "2-комн. кв", "addressStr": "Москва, Очаково микрорайон, ОМ жилой комплекс", "floor": 23, "floorn": 20, "kitchenArea": 0, "livingArea": 0, "priceRur": 29788925, "publishedUserId": 103526792, "totalArea": 59.8, "undergroundInfo": {"lineColor": "FFDF00", "name": "Мичуринский проспект", "type": "mow"}}, {"id": 310096989, "photoUrl": "https://images.cdn-cian.ru/images/2405149675-4.jpg", "roomTitle": "2-комн. кв", "addressStr": "Москва, Павелецкая Сити жилой комплекс", "floor": 28, "floorn": 25, "kitchenArea": 0, "livingArea": 47.8, "priceRur": 30917835, "publishedUserId": 114889818, "totalArea": 71.1, "undergroundInfo": {"lineColor": "00701A", "name": "Павелецкая", "type": "mow"}}, {"id": 313623855, "photoUrl": "https://images.cdn-cian.ru/images/2401862179-4.jpg", "roomTitle": "2-комн. кв", "addressStr": "Москва, проезд 4-й Сетуньский, 10Ас2", "floor": 34, "floorn": 3, "kitchenArea": 6.1, "livingArea": 40, "priceRur": 41176400, "publishedUserId": 127704989, "totalArea": 62.2, "undergroundInfo": {"lineColor": "03238B", "name": "Парк Победы", "type": "mow"}}], "linkToMap": "https://www.cian.ru/map/?engine_version=2&deal_type=sale&offer_type=flat&region=1&minprice=35700000&maxprice=48299999&room2=1&room3=1&zoom=16&center=55.679605%2C37.550333", "isFavorite": false, "offerFoldersCount": 0, "subscription": {"isSubscribed": false}, "priceChanges": [{"changeTime": "2024-09-12T11:25:09.039430+00:00", "priceData": {"currency": "rur", "price": 42000000}}, {"changeTime": "2024-02-07T14:27:41.207428+00:00", "priceData": {"currency": "rur", "price": 37000000}}], "newObject": {"name": "Вавилово", "advantages": [], "specifications": [{"title": "Класс", "value": "Премиум"}, {"title": "Тип дома", "value": "Монолитный"}, {"title": "Парковка", "value": "Подземная, гостевая"}, {"title": "Отделка", "value": ""}, {"title": "Тип комплекса", "value": "Жилой комплекс", "valueTooltipText": "Один или несколько многоквартирных домов, объединённых общей территорией и инфраструктурой."}], "promoInfos": [], "decorations": [], "newbuildingFeatures": {"imagesCount": 3, "firstImageUrl": "https://images.cdn-cian.ru/images/2/343/886/vavilovo-moskva-jk-688343248-6.jpg", "videosCount": 0, "reviewsCount": 27, "hasProgressOfConstructions": false}, "id": 45932, "url": "/zhiloy-kompleks-vavilovo-moskva-45932/", "status": "Сдан", "developer": {"id": 13106, "url": "/zastroishchik-oao-vavilovo-13106/", "name": "ОАО Вавилово", "logoUrl": "/api/get-company-logo/?id=13106&rnd=806447", "stats": {"progress": {"qs": "builder=13106&deal_type=sale&engine_version=2&offer_type=newobject&status%5B0%5D=5002"}, "done": {"text": "1 дом в 1 ЖК", "qs": "builder=13106&deal_type=sale&engine_version=2&offer_type=newobject&show_old_newobjects=1&status%5B0%5D=5004"}}}, "hasLayoutImageOffers": false, "fullUrlWithSubdomain": "https://zhk-vavilovo-i.cian.ru/", "gaLabel": "/sale/jk/mo_id=0/obl_id=1/city_id=1/object_type=2/ga_obj_type=0/spec=none/45932/from_developer=1/nv=0/", "nearbyNewbuildingsMapUrl": "//cian.ru/map/?deal_type=sale&engine_version=2&zoom=12&with_newobject=1&newbuildings_search=true&region=1&center=55.67961,37.550333"}, "company": {"buildingStatus": [{"count": 1, "housesCount": 1, "statusId": 5004}], "categoryId": 2002, "description": "Открытое акционерное общество «Вавилово».", "fromDeveloperPropsCount": null, "hasSpecProject": false, "id": 13106, "isTest": false, "locationIds": [1], "logoUrl": "/api/get-company-logo/?id=13106&rnd=286331", "name": "ОАО Вавилово", "newobjectsCount": 1, "offersCount": 0, "phones": [], "promoCount": 0, "specProjectNewobjectsCount": 0, "status": 12, "website": "https://vavilovo.com/", "yearFoundation": 2016, "reviewStats": {"reviewCount": 27, "reviewCountText": "27 отзывов", "totalRate": 4.7}, "advantages": null, "buildersAuctionRank": null, "email": null, "emailForRequest": null, "headerImageUrl": null, "isReliable": false, "maxBet": null, "newbuildingIds": null, "stats": null, "url": "#", "workYears": null}, "offences": [], "bti": {"houseData": {"yearRelease": 2005, "houseMaterialType": "monolith", "floorMax": 18, "entrances": 5, "flatCount": 257, "isEmergency": false, "demolishedInMoscowProgramm": false, "houseHeatSupplyType": "central", "houseOverhaulFundType": "specialOrg", "houseGasSupplyType": "without", "houseOverlapType": "concrete", "lifts": 17, "seriesName": "Индивидуальный проект"}}, "stats": {"daily": 1, "total": 1049, "totalViewsFormattedString": "1049 просмотров, 1 за сегодня", "totalUniqueViewsFormattedString": "419 уникальных с марта 2024"}, "notes": {}, "agent": {"id": 90141535, "cianUserId": 90141535, "realtyUserId": 90141535, "accountType": "specialist", "companyName": "Омега-Эстейт", "creationDate": "2022-04-22T11:18:05.863000+00:00", "name": "Максим Николаенко", "isPro": true, "phones": [{"confirmed": true}, {"confirmed": true}], "skills": [{"id": 711, "name": "жилая", "parentName": "Продажа недвижимости"}, {"id": 712, "name": "жилая", "parentName": "Аренда недвижимости"}, {"id": 713, "name": "загородная", "parentName": "Продажа недвижимости"}, {"id": 714, "name": "загородная", "parentName": "Аренда недвижимости"}, {"id": 717, "name": "коммерческая", "parentName": "Продажа недвижимости"}, {"id": 718, "name": "коммерческая", "parentName": "Аренда недвижимости"}, {"id": 731, "name": "ипотека", "parentName": "Ипотечное кредитование"}, {"id": 732, "name": "рефинансирование", "parentName": "Ипотечное кредитование"}], "absoluteAvatarUrl": "https://www.cian.ru/api/get-avatar/?i=50240674&t=2&p=2&timestamp=1737480428", "absoluteMiniAvatarUrl": "https://www.cian.ru/api/get-avatar/?i=50240674&t=2&p=1&timestamp=1737480428", "isDeveloper": false, "firstName": "Максим", "lastName": "Николаенко", "parentId": 5556693, "parentCianId": 435272, "experience": "с 2018 года", "isRecidivist": false, "isUserOffersHasErrors": false, "offersCount": 10, "offersLink": "https://www.cian.ru/company/435272/", "availableServices": {"isUploadsAvailable": true, "isCallTrackingAvailable": false, "isPhoneChangingAvailable": false, "isServicePackagesAvailable": false, "canUseHiddenBase": true}, "userType": "realtor_based", "removeCompetitor": false, "status": "hidden", "isSubAgent": true, "isMessagingEnabled": false, "isPassportVerified": true, "isSelfEmployed": false, "isPrivateBroker": false, "masterAgent": {"cianUserId": 435272, "realtyUserId": 5556693, "absoluteAvatarUrl": "https://www.cian.ru/api/get-avatar/?i=136728&t=2&p=2&timestamp=1667308123", "absoluteMiniAvatarUrl": "https://www.cian.ru/api/get-avatar/?i=136728&t=2&p=1&timestamp=1667308123", "experience": "2012", "accountType": "agency", "creationDate": "2013-12-27T10:14:12.157000+00:00", "offersCount": 10}, "isCianPartner": false, "canShowOnline": true, "moderationInfo": {"qualityLevelInfo": {"levelSystemName": "max", "levelName": "Суперагент", "levelOrder": 4, "hasVerifiedDocuments": true, "highResponsibility": true, "isSuperAgent": true, "isSuperHost": false, "isBlocked": false, "showSuperHost": false, "showSuperAgent": true, "showHighResponsibility": true}, "isUserIdentified": true, "isUserIdentifiedByDocuments": true, "showUserIdentifiedByDocuments": false}, "isHidden": true, "metrics": [{"title": "На Циан", "value": "11 лет"}, {"title": "Объектов в работе", "value": "10"}], "agentLists": []}, "specialProject": {"id": "pik", "link": "https://www.cian.ru/map/?builder=9&deal_type=2&with_newobject=1&object_type=2&currency=2&center=55.77228091175091,37.581318235024824&zoom=11&engine_version=2&newbuildings_search=true&is_pik_promo=1&region=1"}, "user": {"isAuthenticated": false, "permissions": {"canModerateUsers": false, "canModerateAnnouncements": false, "canModerateAnnouncementsExpert": false, "canViewUsers": false, "canViewAnnouncements": false}, "ga": {"type": "", "balance": 0, "packages": [], "emailMd5": ""}}, "agentAvailability": {"userId": 5556693, "available": true}, "agentReviews": {"approvedReviewsCount": 4, "entityName": "", "entityRate": 1, "entityRateMax": 5, "entityRateMin": 5, "isNotificationDisabled": true, "isUserMobilePushSubscribed": false, "isUserSubscribed": false, "rateCounts": [{"count": 4, "rate": 5}, {"count": 0, "rate": 4}, {"count": 0, "rate": 3}, {"count": 0, "rate": 2}, {"count": 0, "rate": 1}], "reviews": [{"answers": [], "created": 1659548504, "dislikesCount": 0, "likesCount": 0, "moderation": {"date": 1660020437}, "rate": 5, "reviewId": "8a85dec0-1353-11ed-b62b-f201eccbd5aa", "status": "approved", "text": "Большое спасибо Максиму за консультацию! По общению сразу чувствуется что человек профессионал своего дела и честно отвечает на поставленные вопросы.", "totalAnswers": 0, "updated": 1659548504, "user": {"avatarUrl": "https://www.cian.ru/avatar.axd?i=94132892&t=1&p=2", "id": 94132892, "name": "ID:94132892", "socialNetworks": []}, "userLikeStatus": "unknown"}, {"answers": [], "created": 1660853385, "dislikesCount": 0, "likesCount": 0, "moderation": {"date": 1660912257}, "rate": 5, "reviewId": "b3e6286c-1f31-11ed-bb92-c2b37cdc8015", "status": "approved", "text": "Огромное спасибо за профессиональный подход к делу и отзывчивость. Максим всегда на связи!Будем рекомендовать друзьям и знакомым!", "totalAnswers": 0, "updated": 1660853385, "user": {"avatarUrl": "https://www.cian.ru/avatar.axd?i=94772072&t=1&p=2", "id": 94772072, "name": "ID:94772072", "socialNetworks": []}, "userLikeStatus": "unknown"}, {"answers": [], "created": 1700341875, "dislikesCount": 0, "likesCount": 0, "moderation": {"date": 1700540681}, "rate": 5, "reviewId": "024a847a-8657-11ee-aef0-36dff4cb7275", "status": "approved", "text": "Грамотный специалист! Помог купить квартиру, взял на себя все обязанности по сделке, как оказалось с правильным агентом покупка не так уж и страшна. Рекомендую!", "totalAnswers": 0, "updated": 1700341875, "user": {"avatarUrl": "https://www.cian.ru/avatar.axd?i=59865742&t=1&p=2", "id": 59865742, "name": "ID:59865742", "socialNetworks": []}, "userLikeStatus": "unknown"}, {"answers": [], "created": 1701799478, "dislikesCount": 0, "likesCount": 0, "moderation": {"date": 1701951279}, "rate": 5, "reviewId": "c19bf57c-9398-11ee-8044-aeebb45ab07a", "status": "approved", "text": "Приятно общаться с риелтором который знает свои объекты, пунктуален и вежлив)", "totalAnswers": 0, "updated": 1701799478, "user": {"avatarUrl": "https://www.cian.ru/img/cian/icon_old/100x100.gif", "id": 111045788, "name": "ID:111045788", "socialNetworks": []}, "userLikeStatus": "unknown"}], "subscriptionEmail": "", "totalCount": 4}, "isHiddenByUser": false, "degradationInfo": {}, "priceInfo": {"pricePerSquareValue": 343137}, "offersComparisonStatus": {"status": "available", "description": "Добавить к сравнению"}, "brandingLevel": "firstLevel", "rosreestrInfoV2": {"showCheckedLabel": false}, "isOnlineRegistrationAvailable": false, "factoids": [{"title": "Общая площадь", "icon": "https://images.cdn-cian.ru/imgmobile/icons/offer_card/size.svg", "value": "122,4 м²"}, {"title": "Жилая площадь", "icon": "https://images.cdn-cian.ru/imgmobile/icons/offer_card/plan.svg", "value": "64,1 м²"}, {"title": "Площадь кухни", "icon": "https://images.cdn-cian.ru/imgmobile/icons/offer_card/kitchen.svg", "value": "19,3 м²"}, {"title": "Этаж", "icon": "https://images.cdn-cian.ru/imgmobile/icons/offer_card/floor.svg", "value": "2 из 18"}, {"title": "Год постройки", "icon": "https://images.cdn-cian.ru/imgmobile/icons/offer_card/build_year.svg", "value": "2005"}], "sidebar": [{"title": "Цена за метр", "value": "343 137 ₽/м²"}, {"title": "Условия сделки", "value": "свободная продажа"}, {"title": "Ипотека", "value": "возможна"}], "features": [{"title": "О квартире", "id": "aboutFlat", "features": [{"value": "Вторичка", "label": "Тип жилья"}, {"value": "122,4 м²", "label": "Общая площадь"}, {"value": "64,1 м²", "label": "Жилая площадь"}, {"value": "19,3 м²", "label": "Площадь кухни"}, {"value": "3 м", "label": "Высота потолков"}, {"value": "2 совмещенных", "label": "Санузел"}, {"value": "Во двор", "label": "Вид из окон"}, {"value": "Без ремонта", "label": "Ремонт"}]}, {"title": "О доме", "id": "aboutBuilding", "features": [{"value": "2005", "label": "Год постройки"}, {"value": "Индивидуальный проект", "label": "Строительная серия"}, {"value": "1 пассажирский, 1 грузовой", "label": "Количество лифтов"}, {"value": "Монолитный", "label": "Тип дома"}, {"value": "Железобетонные", "label": "Тип перекрытий"}, {"value": "Подземная", "label": "Парковка"}, {"value": "5", "label": "Подъезды"}, {"value": "Центральное", "label": "Отопление"}, {"value": "Нет", "label": "Аварийность"}]}], "seoData": {"socialNetworksTitle": {"full": "Продаётся, 2-комнатная квартира, за 42 000 000 ₽, 122.4 м², этаж 2/18", "short": "Продаётся, 2-комн. кв., за 42 000 000 ₽"}, "mainTitle": "Продажа двухкомнатной квартиры 122.4м² ул. Архитектора Власова, 6, Москва, ЮЗАО, р-н Ломоносовский м. Профсоюзная - база ЦИАН, объявление 298271416", "description": "➜ Купите двухкомнатную квартиру площадью 122.4м² ул. Архитектора Власова, 6, Москва, ЮЗАО, р-н Ломоносовский м. Профсоюзная. Цена продажи - 42 000 000 руб. Недвижимость на ЦИАН - объявление 298271416", "micromarking": {"@context": "https://schema.org/", "@type": "Product", "name": "", "image": ["https://images.cdn-cian.ru/images/2095952382-1.jpg", "https://images.cdn-cian.ru/images/2095952383-1.jpg", "https://images.cdn-cian.ru/images/2095952387-1.jpg", "https://images.cdn-cian.ru/images/2095952397-1.jpg", "https://images.cdn-cian.ru/images/2095952407-1.jpg"], "description": "Id 1588. Делимся с коллегами 5050. Настоящий бизнес класс в готовом доме от 300.000т. м²О квартире Продается просторная 2хкомнатная квартира, с возможностью перепланировки в две изолированные комнаты. Квартира в качественной и продуманной отделке whitebox, что позволит вам реализовать свои творческие задумки, в процессе ремонта. Комнаты в квартире площадями 41.4 кв.м. и 22.7 кв.м.  О локацииЭто место жительства научной элиты страны, академиков, композиторов, писателей. Дом расположен в современном районе Москвы с устоявшейся инфраструктурой, трехуровневый подземный паркинг, эксплуатируемая кровля на которой вы всегда можете провести время наблюдая панораму города на 360 градусов.  В непосредственной близости расположен знаменитый Черемушкинский рынок, который в 1962 году открывал сам генеральный секретарь Л.И. Брежнев. В ЖК находятся детский сад, школа, медицинские центры.О транспортной доступностиШикарное местоположение комфортно добираться до центра города как общественным транспортом, так и на личном авто. До метро Профсоюзная пешком 10 минут.О документахПолная стоимость в договореКвартира без обремененийСвободная продажа.Ближайшие станции метро по прямойм. Профсоюзная  700 метровм. Новые Черёмушки  900 метровм. Академическая  1600 метров", "sku": 298271416, "brand": {"@type": "Brand", "name": "Циан"}, "review": {"@type": "Review", "reviewRating": {"@type": "Rating", "ratingValue": 4.9, "bestRating": 5}, "author": {"@type": "Person", "name": "Максим Николаенко"}}, "offers": {"@type": "Offer", "url": "https://www.cian.ru/sale/flat/298271416/", "priceCurrency": "RUB", "availability": "https://schema.org/InStock", "price": 42000000}}}, "trackingUrl": "/sale/flat/JK/obl_id=1/city_id=1/object_type=1/ga_obj_type=2/spec=agent/298271416/from_developer=0/repres=0/owner=0/pod_snos=0/nv=0/", "amenities": [], "newbuildingRating": 4.7, "offerPrice": "42 000 000 ₽", "newbuildingFlatSaleQueryString": "/cat.php?deal_type=sale&engine_version=2&object_type%5B0%5D=2&offer_type=flat&region=1&from_developer=1&maxprice=47000000&decorations_list%5B0%5D=fine&decorations_list%5B1%5D=fineWithFurniture&decorations_list%5B2%5D=preFine"}, "promotionsVillageData": {}, "offerStatsPopup": {"dataStats": null, "isOpen": false, "messageError": "", "statusFetch": 0}, "pageData": {"dealType": "sale", "offerId": 298271416, "offerType": "flat", "subdomain": "www"}, "phoneCollapse": false, "phoneWarning": {"isOpen": false, "target": null}, "printModal": {"isCommentsVisible": true, "isOpen": false, "isPhonesVisible": true, "isPrintModeEnabled": false}, "pushSubscribed": false, "reclaimModal": {"errorMessage": "", "isOpen": false, "statusFetch": "none"}, "remove": {"activeFrame": "initial", "isOpen": false, "status": "default"}, "seoLinks": {"isLoad": false, "seoLinks": {"seoBlocks": [{"title": "Дополнительные предложения по продаже", "links": [{"name": "2-комнатные квартиры без ремонта рядом с метро Авиамоторная", "uri": "/kupit-2-komnatnuyu-kvartiru-bez-remonta-moskva-metro-aviamotornaya/"}]}]}}, "serviceBaseUrl": "https://service.cian.ru/", "similarOffers": {"userBased": {"list": [], "withoutCompetitors": false, "modelVersion": ""}, "itemBased": {"list": [], "withoutCompetitors": false, "modelVersion": ""}, "historyBased": {"list": [], "withoutCompetitors": false, "modelVersion": ""}, "newItemBased": {"list": [], "withoutCompetitors": false, "modelVersion": ""}, "newobjectItemBased": {"list": [], "withoutCompetitors": false, "modelVersion": ""}}, "specialPromoInfo": null, "subscriptionPriceChangesPopup": {"error": "", "isEmailConfirmed": false, "isOpen": false, "statusFetch": "none"}, "tracking": {"user": {"abGroup": 0, "type": "not_authorized"}, "page": {"customPageURL": "/sale/flat/mo_id=0/obl_id=1/city_id=1/object_type=1/ga_obj_type=2/spec=agent/298271416/from_developer=0/repres=0/owner=0/pod_snos=0/nv=0/", "dealType": "sale", "objectType": "flat_old", "offerID": 298271416, "offerPhone": "+79810865337", "pageType": "Card", "region": "0-1-1", "siteType": "desktop", "breadCrumbs": ["Недвижимость в Москве", "Продажа", "Продажа 2-комнатных квартир в Москве", "ЮЗАО", "Ломоносовский", "метро Профсоюзная", "улица Архитектора Власова"], "extra": {"cplDynamicCalltracking": 0, "cplCalltracking": 0, "additional_price": 343137, "category": "flatSale", "adfox": {"status": 0}}}}, "viewedSimilar": {"ids": []}, "ebcInfo": {"user": {"abGroup": 0, "isAuthorized": false}, "page": {"breadCrumbs": ["Недвижимость в Москве", "Продажа", "Продажа 2-комнатных квартир в Москве", "ЮЗАО", "Ломоносовский", "метро Профсоюзная", "улица Архитектора Власова"], "offerID": 298271416}}, "mlSearchRegions": [], "isMlSearchForAllEnabled": true, "isBrandingAvailable": true, "isCountrysideOffersBuilderBadgeEnabled": true, "isHomeowner": false, "soprApi": "https://sopr-api.cian.ru/", "widgetsMarkup": {}, "infrastructureMap": {"isLoaded": false}, "infrastructureCategories": [], "isCountrysidePromoEnabled": true, "knAuctionCompanies": [], "auctionBanks": [], "dealRent": {"isOpen": false, "isLoading": false, "error": null, "isSuccessModal": false, "isSendSimilarModal": false, "isSimilarSuccessModal": false, "isFailureModal": false, "isPrefetching": false, "phoneConfirmed": false, "isSendSMSLoading": false, "secondsToRetry": 60, "isEntryToShowOpen": false, "isEntryToShowSuccessModal": false, "initialFormState": {"personsCount": 1, "personsInfo": "", "childrenCount": 0, "childrenInfo": [], "petsCount": 0, "petsInfo": "", "comment": "", "activityScope": "", "name": "", "isAgent": false, "phone": "", "smsCode": ""}}, "renterForm": {"isOpen": false, "isLoading": false, "error": null, "isSuccessModal": false, "isFailureModal": false, "isPrefetching": false, "phoneConfirmed": false, "isSendSMSLoading": false, "secondsToRetry": 60, "currentStep": "onboarding", "initialFormState": {"personsCount": 1, "personsInfo": "", "childrenCount": 0, "childrenInfo": [], "petsCount": 0, "petsInfo": "", "comment": "", "activityScope": "", "name": "", "isAgent": false, "phone": "", "smsCode": ""}}, "complaintPopupOpen": false, "notAvailablePopupOpen": false, "featureToggle": {"utilitiesTermsSettings": {"isUtilitiesTermsEnabled": true, "useIncludeUtilitiesTermsRegions": true, "excludeUtilitiesTermsRegions": [4959, 4606, 4588, 2], "includeUtilitiesTermsRegions": [1, 4593]}, "newbuildingBlackFridaySettings": {"promoDatesText": ""}, "isFavoritesFolderEnabled": true, "isBuyAnalyticsButtonEnabled": false, "isLegalDocsUrlForCommercialReportsEnabled": true, "isCommercialNewVatTextEnabled": true, "isMortgageBrokerBannerEnabled": true, "newbuildingMortgageCalculatorMicrofrontEnabled": false, "isBestPlaceCheckoutEnabled": false, "isConsultantMessageButtonEnabled": false, "isChatOnboardingEnabled": false, "isWebimChatOnboardingEnabled": false}, "dealRentVasCost": 0, "isHomeownerDocsRequired": false, "offersHistory": {"data": {"listing": {"isFetching": false, "isError": false, "data": null, "isLoadMore": false}, "listingSpoiler": {"isFetching": false, "isError": false, "data": null, "isLoadMore": false}, "offers": {"isFetching": false, "isError": false, "isAuthError": false, "isLoadMore": false, "data": {}}}, "roomsFilterActiveValue": "all", "statusFilterActiveValue": "all", "page": 1, "resultsOnPage": 10, "activeOfferId": null, "isFiltersChanged": false, "viewedOffers": [], "defaultFilters": {}, "haveAdminAccess": false}, "offerValuation": {"data": null, "isFetching": false, "isError": false, "estimationPeriod": null}, "showAnalyticsButton": false, "entryToShowEnabled": false, "newStatsEnabled": false, "favoritesAssignWidget": {"folders": [], "selected": {}, "initialSelectedFolderIds": [], "savedOfferId": [], "savedInFolders": null, "userHasFolders": false, "showFoldersList": false, "showModalCreateFolder": false, "showOnBoardingDelete": false, "showNotification": false, "isListLoading": false, "canLoadMore": false}, "banksList": {"list": [{"id": "bank-sberbank", "enabled": false, "logo": "https://static.cdn-cian.ru/frontend/finance-assets/banks/logos/sber.svg", "icon": "https://static.cdn-cian.ru/frontend/finance-assets/bages/sber.svg", "name": "Сбербанк", "integration": "none"}, {"id": "bank-vtb-new", "enabled": true, "logo": "https://static.cdn-cian.ru/frontend/finance-assets/banks/logos/vtb.svg", "icon": "https://static.cdn-cian.ru/frontend/finance-assets/bages/vtb.svg", "fullsizeIcon": "https://static.cdn-cian.ru/frontend/finance-assets/fullsize/VTB_color.svg", "name": "ВТБ", "legalName": "Банк ВТБ (ПАО)", "integration": "custom", "inn": "7702070139"}, {"id": "bank-psb", "enabled": false, "logo": "https://static.cdn-cian.ru/frontend/finance-assets/banks/logos/psb.svg", "icon": "https://static.cdn-cian.ru/frontend/finance-assets/bages/psb.svg", "fullsizeIcon": "https://static.cdn-cian.ru/frontend/finance-assets/fullsize/PSB_color.svg", "name": "ПСБ", "legalName": "ПAO «Промсвязьбанк»", "integration": "none", "inn": "7744000912"}, {"id": "bank-gpb", "enabled": true, "logo": "https://static.cdn-cian.ru/frontend/finance-assets/banks/logos/gpb.svg", "icon": "https://static.cdn-cian.ru/frontend/finance-assets/bages/gazprom-bank.svg", "fullsizeIcon": "https://static.cdn-cian.ru/frontend/finance-assets/fullsize/GAZPROM_color.svg", "name": "Газпромбанк", "legalName": "Банк ГПБ (АО)", "integration": "light", "env": ["dev", "ote"], "inn": "7744001497"}, {"id": "bank-sovcom", "enabled": true, "logo": "https://static.cdn-cian.ru/frontend/finance-assets/banks/logos/sovcom.svg", "icon": "https://static.cdn-cian.ru/frontend/finance-assets/bages/sovkom-bank.svg", "fullsizeIcon": "https://static.cdn-cian.ru/frontend/finance-assets/fullsize/SOVKOMBANK_color.svg", "name": "Совкомбанк", "legalName": "ПАО «Совкомбанк»", "integration": "api", "inn": "4401116480"}, {"id": "bank-raif", "enabled": false, "logo": "https://static.cdn-cian.ru/frontend/finance-assets/banks/logos/raif.svg", "icon": "https://static.cdn-cian.ru/frontend/finance-assets/bages/raiffeisen-bank.svg", "fullsizeIcon": "https://static.cdn-cian.ru/frontend/finance-assets/fullsize/RAIFF_color.svg", "name": "Райффайзенбанк", "legalName": "АО «Райффайзенбанк»", "integration": "none", "inn": "7744000302"}, {"id": "bank-rshb", "enabled": false, "logo": "https://static.cdn-cian.ru/frontend/finance-assets/banks/logos/rshb.svg", "icon": "https://static.cdn-cian.ru/frontend/finance-assets/bages/rshb.svg", "fullsizeIcon": "https://static.cdn-cian.ru/frontend/finance-assets/fullsize/ROSSELHOZ_color.svg", "name": "Россельхозбанк", "legalName": "АО «Россельхозбанк»", "integration": "none", "inn": "7725114488"}, {"id": "bank-alfa", "enabled": true, "logo": "https://static.cdn-cian.ru/frontend/finance-assets/banks/logos/alfa.svg", "icon": "https://static.cdn-cian.ru/frontend/finance-assets/bages/alfa.svg", "fullsizeIcon": "https://static.cdn-cian.ru/frontend/finance-assets/fullsize/ALFA_color.svg", "name": "Альфа-Банк", "legalName": "АО «Альфа-Банк»", "integration": "light", "inn": "7728168971"}, {"id": "bank-bgf", "enabled": true, "logo": "https://static.cdn-cian.ru/frontend/finance-assets/banks/logos/bgf.svg", "icon": "https://static.cdn-cian.ru/frontend/finance-assets/bages/bgf.svg", "fullsizeIcon": "https://static.cdn-cian.ru/frontend/finance-assets/fullsize/BGF_color.svg", "name": "БЖФ", "notPayroll": true, "legalName": "АО «Банк БЖФ»", "integration": "api", "env": ["ote"], "inn": "7709056550"}, {"id": "bank-ubrir", "enabled": false, "logo": "https://static.cdn-cian.ru/frontend/finance-assets/banks/logos/ubrir.svg", "icon": "https://static.cdn-cian.ru/frontend/finance-assets/bages/ubrir.svg", "fullsizeIcon": "https://static.cdn-cian.ru/frontend/finance-assets/fullsize/UBRIR_color.svg", "name": "УБРиР", "legalName": "ПАО КБ «УБРИР»", "integration": "light", "inn": "6608008004"}, {"id": "bank-open", "enabled": false, "logo": "https://static.cdn-cian.ru/frontend/finance-assets/banks/logos/open.svg", "icon": "https://static.cdn-cian.ru/frontend/finance-assets/bages/open.svg", "fullsizeIcon": "https://static.cdn-cian.ru/frontend/finance-assets/fullsize/OPEN_color.svg", "name": "Открытие", "legalName": "ПАО Банк «ФК Открытие»", "integration": "none", "requireSpouseInfo": true, "inn": "7706092528"}, {"id": "bank-uralsib", "enabled": true, "logo": "https://static.cdn-cian.ru/frontend/finance-assets/banks/logos/uralsib.svg", "icon": "https://static.cdn-cian.ru/frontend/finance-assets/bages/uralsib.svg", "fullsizeIcon": "https://static.cdn-cian.ru/frontend/finance-assets/fullsize/URALSIB_color.svg", "name": "Уралсиб", "legalName": "ПАО «Банк Уралсиб»", "integration": "light", "inn": "0274062111"}, {"id": "bank-domrf", "enabled": true, "logo": "https://static.cdn-cian.ru/frontend/finance-assets/banks/logos/domrf.svg", "icon": "https://static.cdn-cian.ru/frontend/finance-assets/bages/domrf.svg", "fullsizeIcon": "https://static.cdn-cian.ru/frontend/finance-assets/fullsize/DOMRF_color.svg", "name": "Банк ДОМ.РФ", "legalName": "АО «Банк ДОМ.РФ", "integration": "light", "inn": "7725038124"}, {"id": "bank-domrf2", "enabled": true, "logo": "https://static.cdn-cian.ru/frontend/finance-assets/banks/logos/domrf.svg", "icon": "https://static.cdn-cian.ru/frontend/finance-assets/bages/domrf.svg", "fullsizeIcon": "https://static.cdn-cian.ru/frontend/finance-assets/fullsize/DOMRF_color.svg", "name": "Банк ДОМ.РФ Тест", "legalName": "АО «Банк ДОМ.РФ", "integration": "light", "env": ["ote"], "inn": "7725038124"}, {"id": "bank-t", "enabled": true, "logo": "https://static.cdn-cian.ru/frontend/finance-assets/banks/logos/tbank.svg", "icon": "https://static.cdn-cian.ru/frontend/finance-assets/bages/tbank.svg", "fullsizeIcon": "https://static.cdn-cian.ru/frontend/finance-assets/fullsize/TBANK_color.svg", "name": "Т-Банк", "legalName": "АО «ТБАНК»", "integration": "light", "inn": "7710140679"}, {"id": "bank-unicredit", "enabled": false, "logo": "https://static.cdn-cian.ru/frontend/finance-assets/banks/logos/unicredit.svg", "name": "ЮниКредит Банк", "integration": "none"}, {"id": "bank-mkb", "enabled": true, "logo": "https://static.cdn-cian.ru/frontend/finance-assets/banks/logos/mkb.svg", "icon": "https://static.cdn-cian.ru/frontend/finance-assets/bages/mkb.svg", "fullsizeIcon": "https://static.cdn-cian.ru/frontend/finance-assets/fullsize/MKB_color.svg", "name": "МКБ", "legalName": "ПАО «МКБ»", "integration": "light", "inn": "7734202860"}, {"id": "bank-personal-loan-emulator", "enabled": true, "logo": "https://static.cdn-cian.ru/frontend/finance-assets/banks/logos/bank-personal-loan-emulator.svg", "name": "Циан Банк", "integration": "api", "env": ["ote"]}, {"id": "bank-mts", "enabled": true, "logo": "https://static.cdn-cian.ru/frontend/finance-assets/banks/logos/mts.svg", "name": "МТС-Банк", "legalName": "ПАО «МТС-Банк»", "integration": "api", "env": ["ote"], "inn": "7702045051"}], "randomList": [{"id": "bank-t", "enabled": true, "logo": "https://static.cdn-cian.ru/frontend/finance-assets/banks/logos/tbank.svg", "icon": "https://static.cdn-cian.ru/frontend/finance-assets/bages/tbank.svg", "fullsizeIcon": "https://static.cdn-cian.ru/frontend/finance-assets/fullsize/TBANK_color.svg", "name": "Т-Банк", "legalName": "АО «ТБАНК»", "integration": "light", "inn": "7710140679"}, {"id": "bank-domrf", "enabled": true, "logo": "https://static.cdn-cian.ru/frontend/finance-assets/banks/logos/domrf.svg", "icon": "https://static.cdn-cian.ru/frontend/finance-assets/bages/domrf.svg", "fullsizeIcon": "https://static.cdn-cian.ru/frontend/finance-assets/fullsize/DOMRF_color.svg", "name": "Банк ДОМ.РФ", "legalName": "АО «Банк ДОМ.РФ", "integration": "light", "inn": "7725038124"}, {"id": "bank-sovcom", "enabled": true, "logo": "https://static.cdn-cian.ru/frontend/finance-assets/banks/logos/sovcom.svg", "icon": "https://static.cdn-cian.ru/frontend/finance-assets/bages/sovkom-bank.svg", "fullsizeIcon": "https://static.cdn-cian.ru/frontend/finance-assets/fullsize/SOVKOMBANK_color.svg", "name": "Совкомбанк", "legalName": "ПАО «Совкомбанк»", "integration": "api", "inn": "4401116480"}, {"id": "bank-alfa", "enabled": true, "logo": "https://static.cdn-cian.ru/frontend/finance-assets/banks/logos/alfa.svg", "icon": "https://static.cdn-cian.ru/frontend/finance-assets/bages/alfa.svg", "fullsizeIcon": "https://static.cdn-cian.ru/frontend/finance-assets/fullsize/ALFA_color.svg", "name": "Альфа-Банк", "legalName": "АО «Альфа-Банк»", "integration": "light", "inn": "7728168971"}]}, "mortgagePromoDesign": null, "flatTourBooking": {"isTooltipOpen": false, "schedule": null}, "crossedOutPriceExcludeNewbuildingIds": [6190, 7904, 8753, 30342, 2096941, 1611, 34895], "comparisonNotification": null, "rs": {"buyAnalyticsFreeReportData": {"name": "БЦ Саммит. Москва, Тверская улица, 22.", "date": "от 13.04.2022", "url": "https://static.cdn-cian.ru/frontend/iap-statics-frontend/others/demo-analytics-report.pdf"}, "newbuildingBookingForm": {"enabled": true, "regions": [1, 4593, 2, 4588, 4777, 4897], "builders": [8079, 6399, 8114, 8110, 9164, 8136, 1301, 9591, 14557, 8130, 2351, 8113, 9037, 6381, 13100, 8077, 8160, 9034, 9079, 10109, 10814, 8131, 6399, 5747, 6381, 7042, 11623, 6008, 7046, 980, 7043, 11628, 8732, 6114, 15624, 9542, 17196, 15029, 7066, 8229, 7671, 15417, 8075, 17667, 8314, 14380, 9596, 15990, 18449, 14483, 18537, 10047, 9207, 8181, 8177, 17296, 13100, 10254, 10366, 10278, 10243, 18014, 9912, 14296, 10260, 15277, 15298, 15776, 17267, 14733, 10364, 15372, 18001, 14653, 18243, 10255, 10286, 6399, 14860, 980, 8602, 8624, 18773, 8664, 14375, 8665, 9817, 5747, 9164, 17534, 17605, 18729]}, "buyAnalyticsLegalDocsUrl": "https://www.cian.ru/legal-documents/dogovor_publichnaya_oferta_ob_okazanii_uslugi_analiticheskij_otchet_informacionno_analiticheskoj_platformy_iap_v_vydache_marketplejsa_326", "bestPlaceAnalyticsReportExampleUrl": "https://files.cian.ru/files/commercial/geo-analytics/report_example.pdf", "bestPlaceReportLegalDocsUrl": "https://www.cian.ru/legal-documents/dogovor_publichnaya_oferta_ob_okazanii_uslugi_otchet_o_privlekatelnosti_obekta_0", "bestPlaceReportBaseUrl": "https://cian.bestplace.pro/location-report", "bestPlaceReportProviderInfo": "Услугу предоставляет ООО «Бест-Плейс», ОГРН: 5167746245960"}, "isQaMode": false, "isRenterFormEnabled": true, "buyAnalyticsModal": {"isOpened": false, "reportPrice": 0, "property": null, "status": null, "paymentUrl": null, "transactionId": null, "userEmail": "", "isReportAvailable": false, "openReportAfterAuth": false}, "bestPlaceModal": {"isOpened": false}, "recommendedVillages": null, "genplan": null, "adfoxOffer": {"response": {"status": "ok", "data": {"unicomLinkParams": {"puid12": 298271416, "puid13": 42000000, "puid14": "Москва, район Ломоносовский, ул. Архитектора Власова, 6", "puid15": "https://images.cdn-cian.ru/images/2095952382-1.jpg", "puid16": "вторичка, монолитный"}, "offerType": "flat", "params": {"puid1": "deal_type_sale", "puid2": "offer_flat", "puid36": 1, "puid3": "sale_type_second", "puid4": "offer_type_2", "puid5": "obl_id_1", "puid6": "40001_50000", "puid7": "2323", "puid8": 42000000, "puid9": 104, "puid10": "no_agent", "puid16": "false", "puid17": "false", "puid18": 45932, "puid19": "not_video", "puid41": "premium"}, "dealType": "sale", "ymEvents": {"onPriceChange": {"target": "sb_mimo_premium", "eventName": "reachGoal"}}}}, "statusCode": 200}, "isStartChatWidgetInDropdown": false, "rosreestr": null, "bestPlaceAnalytics": {"amount": null, "discount": null, "discountPrice": null, "paymentUrl": null, "status": null, "statusMessage": null, "userEmail": null}, "buildersProjectsLocations": [], "suburbanBuildersProjects": [], "reviewsGoToAppModal": {"isOpen": false}, "valuationTraps": {"isMyHomeObjectsExists": false}, "dailyrentBooking": {"general": {"isLoading": false, "price": "", "paymentSummary": null, "defaultBookingMessage": "", "error": ""}, "calendar": {"isOpen": false, "canBeBooked": true, "initialLoading": false, "daysAvailability": [], "showBookingCalendar": false, "dateInputText": "", "dates": {}}, "guests": {"isOpen": false, "guestsCount": 1, "minGuestsCount": 1, "maxGuestsCount": 99}}, "dailyrentActionType": null, "bannerRotation": 0, "comparison": {"comparison": {"props": [], "offers": [], "notFoundUrl": "/kupit-kvartiru/", "seoData": {"h1": "Сравнение квартир", "title": "Сравнение квартир в Москве - ЦИАН", "description": "Сравнение квартир в Москве по цене, площади и другим параметрам. Выбирайте на ЦИАН."}}}, "chatOnboarding": {"wasChatOpened": false}}